{"nodes":[{"id":"mdpi_ic_launcher_round_orbit_logo","label":"Android MDPI Round Launcher Orbit Logo","file_type":"image","source_file":"android/app/src/main/res/mipmap-mdpi/ic_launcher_round.png","source_location":null,"source_url":null,"captured_at":null,"author":null,"contributor":null},{"id":"mdpi_splash_orbit_logo","label":"Android MDPI Splash Orbit Logo","file_type":"image","source_file":"android/app/src/main/res/mipmap-mdpi/splash.png","source_location":null,"source_url":null,"captured_at":null,"author":null,"contributor":null},{"id":"xhdpi_ic_launcher_orbit_logo","label":"Android XHDPI Launcher Orbit Logo","file_type":"image","source_file":"android/app/src/main/res/mipmap-xhdpi/ic_launcher.png","source_location":null,"source_url":null,"captured_at":null,"author":null,"contributor":null},{"id":"xhdpi_ic_launcher_foreground_orbit_logo","label":"Android XHDPI Launcher Foreground Orbit Logo","file_type":"image","source_file":"android/app/src/main/res/mipmap-xhdpi/ic_launcher_foreground.png","source_location":null,"source_url":null,"captured_at":null,"author":null,"contributor":null},{"id":"xhdpi_ic_launcher_round_orbit_logo","label":"Android XHDPI Round Launcher Orbit Logo","file_type":"image","source_file":"android/app/src/main/res/mipmap-xhdpi/ic_launcher_round.png","source_location":null,"source_url":null,"captured_at":null,"author":null,"contributor":null},{"id":"xhdpi_splash_orbit_logo","label":"Android XHDPI Splash Orbit Logo","file_type":"image","source_file":"android/app/src/main/res/mipmap-xhdpi/splash.png","source_location":null,"source_url":null,"captured_at":null,"author":null,"contributor":null},{"id":"xxhdpi_ic_launcher_orbit_logo","label":"Android XXHDPI Launcher Orbit Logo","file_type":"image","source_file":"android/app/src/main/res/mipmap-xxhdpi/ic_launcher.png","source_location":null,"source_url":null,"captured_at":null,"author":null,"contributor":null},{"id":"xxhdpi_ic_launcher_foreground_orbit_logo","label":"Android XXHDPI Launcher Foreground Orbit Logo","file_type":"image","source_file":"android/app/src/main/res/mipmap-xxhdpi/ic_launcher_foreground.png","source_location":null,"source_url":null,"captured_at":null,"author":null,"contributor":null},{"id":"xxhdpi_ic_launcher_round_orbit_logo","label":"Android XXHDPI Round Launcher Orbit Logo","file_type":"image","source_file":"android/app/src/main/res/mipmap-xxhdpi/ic_launcher_round.png","source_location":null,"source_url":null,"captured_at":null,"author":null,"contributor":null},{"id":"xxhdpi_splash_orbit_logo","label":"Android XXHDPI Splash Orbit Logo","file_type":"image","source_file":"android/app/src/main/res/mipmap-xxhdpi/splash.png","source_location":null,"source_url":null,"captured_at":null,"author":null,"contributor":null},{"id":"xxxhdpi_ic_launcher_orbit_logo","label":"Android XXXHDPI Launcher Orbit Logo","file_type":"image","source_file":"android/app/src/main/res/mipmap-xxxhdpi/ic_launcher.png","source_location":null,"source_url":null,"captured_at":null,"author":null,"contributor":null},{"id":"xxxhdpi_ic_launcher_foreground_orbit_logo","label":"Android XXXHDPI Launcher Foreground Orbit Logo","file_type":"image","source_file":"android/app/src/main/res/mipmap-xxxhdpi/ic_launcher_foreground.png","source_location":null,"source_url":null,"captured_at":null,"author":null,"contributor":null},{"id":"xxxhdpi_ic_launcher_round_orbit_logo","label":"Android XXXHDPI Round Launcher Orbit Logo","file_type":"image","source_file":"android/app/src/main/res/mipmap-xxxhdpi/ic_launcher_round.png","source_location":null,"source_url":null,"captured_at":null,"author":null,"contributor":null},{"id":"xxxhdpi_splash_orbit_logo","label":"Android XXXHDPI Splash Orbit Logo","file_type":"image","source_file":"android/app/src/main/res/mipmap-xxxhdpi/splash.png","source_location":null,"source_url":null,"captured_at":null,"author":null,"contributor":null},{"id":"github_logo_black_wordmark","label":"GitHub Black Wordmark","file_type":"image","source_file":"assets/GitHub_Logo.png","source_location":null,"source_url":null,"captured_at":null,"author":null,"contributor":null},{"id":"github_logo_white_wordmark","label":"GitHub White Wordmark","file_type":"image","source_file":"assets/GitHub_Logo_White.png","source_location":null,"source_url":null,"captured_at":null,"author":null,"contributor":null},{"id":"album_placeholder_disc_icon","label":"Album Placeholder Disc Icon","file_type":"image","source_file":"assets/album.png","source_location":null,"source_url":null,"captured_at":null,"author":null,"contributor":null},{"id":"artist_placeholder_avatar_note_icon","label":"Artist Placeholder Avatar Note Icon","file_type":"image","source_file":"assets/artist.png","source_location":null,"source_url":null,"captured_at":null,"author":null,"contributor":null},{"id":"black_button_buy_me_a_coffee_banner","label":"Buy Me a Coffee Black CTA Banner","file_type":"image","source_file":"assets/black-button.png","source_location":null,"source_url":null,"captured_at":null,"author":null,"contributor":null},{"id":"cover_music_note_icon","label":"Cover Music Note Icon","file_type":"image","source_file":"assets/cover.jpg","source_location":null,"source_url":null,"captured_at":null,"author":null,"contributor":null}],"edges":[{"source":"mdpi_ic_launcher_round_orbit_logo","target":"xhdpi_ic_launcher_round_orbit_logo","relation":"semantically_similar_to","confidence":"INFERRED","confidence_score":0.95,"source_file":"android/app/src/main/res/mipmap-mdpi/ic_launcher_round.png","source_location":null,"weight":1.0},{"source":"xxhdpi_ic_launcher_round_orbit_logo","target":"xhdpi_ic_launcher_round_orbit_logo","relation":"semantically_similar_to","confidence":"INFERRED","confidence_score":0.96,"source_file":"android/app/src/main/res/mipmap-xxhdpi/ic_launcher_round.png","source_location":null,"weight":1.0},{"source":"xxxhdpi_ic_launcher_round_orbit_logo","target":"xhdpi_ic_launcher_round_orbit_logo","relation":"semantically_similar_to","confidence":"INFERRED","confidence_score":0.96,"source_file":"android/app/src/main/res/mipmap-xxxhdpi/ic_launcher_round.png","source_location":null,"weight":1.0},{"source":"xxhdpi_ic_launcher_orbit_logo","target":"xhdpi_ic_launcher_orbit_logo","relation":"semantically_similar_to","confidence":"INFERRED","confidence_score":0.97,"source_file":"android/app/src/main/res/mipmap-xxhdpi/ic_launcher.png","source_location":null,"weight":1.0},{"source":"xxxhdpi_ic_launcher_orbit_logo","target":"xhdpi_ic_launcher_orbit_logo","relation":"semantically_similar_to","confidence":"INFERRED","confidence_score":0.97,"source_file":"android/app/src/main/res/mipmap-xxxhdpi/ic_launcher.png","source_location":null,"weight":1.0},{"source":"xxhdpi_ic_launcher_foreground_orbit_logo","target":"xhdpi_ic_launcher_foreground_orbit_logo","relation":"semantically_similar_to","confidence":"INFERRED","confidence_score":0.97,"source_file":"android/app/src/main/res/mipmap-xxhdpi/ic_launcher_foreground.png","source_location":null,"weight":1.0},{"source":"xxxhdpi_ic_launcher_foreground_orbit_logo","target":"xhdpi_ic_launcher_foreground_orbit_logo","relation":"semantically_similar_to","confidence":"INFERRED","confidence_score":0.97,"source_file":"android/app/src/main/res/mipmap-xxxhdpi/ic_launcher_foreground.png","source_location":null,"weight":1.0},{"source":"mdpi_splash_orbit_logo","target":"xhdpi_splash_orbit_logo","relation":"semantically_similar_to","confidence":"INFERRED","confidence_score":0.95,"source_file":"android/app/src/main/res/mipmap-mdpi/splash.png","source_location":null,"weight":1.0},{"source":"xxhdpi_splash_orbit_logo","target":"xhdpi_splash_orbit_logo","relation":"semantically_similar_to","confidence":"INFERRED","confidence_score":0.96,"source_file":"android/app/src/main/res/mipmap-xxhdpi/splash.png","source_location":null,"weight":1.0},{"source":"xxxhdpi_splash_orbit_logo","target":"xhdpi_splash_orbit_logo","relation":"semantically_similar_to","confidence":"INFERRED","confidence_score":0.96,"source_file":"android/app/src/main/res/mipmap-xxxhdpi/splash.png","source_location":null,"weight":1.0},{"source":"xhdpi_ic_launcher_foreground_orbit_logo","target":"xhdpi_ic_launcher_orbit_logo","relation":"conceptually_related_to","confidence":"INFERRED","confidence_score":0.88,"source_file":"android/app/src/main/res/mipmap-xhdpi/ic_launcher_foreground.png","source_location":null,"weight":1.0},{"source":"xhdpi_ic_launcher_round_orbit_logo","target":"xhdpi_ic_launcher_orbit_logo","relation":"conceptually_related_to","confidence":"INFERRED","confidence_score":0.9,"source_file":"android/app/src/main/res/mipmap-xhdpi/ic_launcher_round.png","source_location":null,"weight":1.0},{"source":"xhdpi_splash_orbit_logo","target":"xhdpi_ic_launcher_orbit_logo","relation":"conceptually_related_to","confidence":"INFERRED","confidence_score":0.9,"source_file":"android/app/src/main/res/mipmap-xhdpi/splash.png","source_location":null,"weight":1.0},{"source":"github_logo_white_wordmark","target":"github_logo_black_wordmark","relation":"semantically_similar_to","confidence":"INFERRED","confidence_score":0.99,"source_file":"assets/GitHub_Logo_White.png","source_location":null,"weight":1.0},{"source":"album_placeholder_disc_icon","target":"cover_music_note_icon","relation":"semantically_similar_to","confidence":"INFERRED","confidence_score":0.82,"source_file":"assets/album.png","source_location":null,"weight":1.0},{"source":"artist_placeholder_avatar_note_icon","target":"cover_music_note_icon","relation":"conceptually_related_to","confidence":"INFERRED","confidence_score":0.8,"source_file":"assets/artist.png","source_location":null,"weight":1.0},{"source":"artist_placeholder_avatar_note_icon","target":"album_placeholder_disc_icon","relation":"conceptually_related_to","confidence":"INFERRED","confidence_score":0.84,"source_file":"assets/artist.png","source_location":null,"weight":1.0},{"source":"cover_music_note_icon","target":"album_placeholder_disc_icon","relation":"conceptually_related_to","confidence":"INFERRED","confidence_score":0.76,"source_file":"assets/cover.jpg","source_location":null,"weight":1.0},{"source":"black_button_buy_me_a_coffee_banner","target":"github_logo_black_wordmark","relation":"conceptually_related_to","confidence":"AMBIGUOUS","confidence_score":0.24,"source_file":"assets/black-button.png","source_location":null,"weight":1.0},{"source":"black_button_buy_me_a_coffee_banner","target":"github_logo_white_wordmark","relation":"conceptually_related_to","confidence":"AMBIGUOUS","confidence_score":0.22,"source_file":"assets/black-button.png","source_location":null,"weight":1.0}],"hyperedges":[{"id":"android_orbit_logo_asset_family","label":"Android Orbit Logo Asset Family","nodes":["mdpi_ic_launcher_round_orbit_logo","mdpi_splash_orbit_logo","xhdpi_ic_launcher_orbit_logo","xhdpi_ic_launcher_foreground_orbit_logo","xhdpi_ic_launcher_round_orbit_logo","xhdpi_splash_orbit_logo","xxhdpi_ic_launcher_orbit_logo","xxhdpi_ic_launcher_foreground_orbit_logo","xxhdpi_ic_launcher_round_orbit_logo","xxhdpi_splash_orbit_logo","xxxhdpi_ic_launcher_orbit_logo","xxxhdpi_ic_launcher_foreground_orbit_logo","xxxhdpi_ic_launcher_round_orbit_logo","xxxhdpi_splash_orbit_logo"],"relation":"form","confidence":"INFERRED","confidence_score":0.93,"source_file":"android/app/src/main/res/mipmap-xhdpi/ic_launcher.png"},{"id":"music_metadata_placeholder_assets","label":"Music Metadata Placeholder Assets","nodes":["album_placeholder_disc_icon","artist_placeholder_avatar_note_icon","cover_music_note_icon"],"relation":"participate_in","confidence":"INFERRED","confidence_score":0.82,"source_file":"assets/cover.jpg"},{"id":"community_branding_cta_assets","label":"Community Branding and CTA Assets","nodes":["github_logo_black_wordmark","github_logo_white_wordmark","black_button_buy_me_a_coffee_banner"],"relation":"participate_in","confidence":"INFERRED","confidence_score":0.66,"source_file":"assets/black-button.png"}],"input_tokens":0,"output_tokens":0}